[
  {
    "HowToGet": "Shop",
    "Id": 0,
    "Season": 0
  },
  {
    "HowToGet": "Shop",
    "Id": 532,
    "Season": 1
  },
  {
    "HowToGet": "Shop",
    "Id": 533,
    "Season": 1
  },
  {
    "HowToGet": "Shop",
    "Id": 534,
    "Season": 1
  },
  {
    "HowToGet": "Shop",
    "Id": 535,
    "Season": 1
  },
  {
    "HowToGet": "Shop",
    "Id": 537,
    "Season": 1
  },
  {
    "HowToGet": "Shop",
    "Id": 539,
    "Season": 1
  },
  {
    "HowToGet": "Shop",
    "Id": 529,
    "Season": 1
  },
  {
    "HowToGet": "Shop",
    "Id": 540,
    "Season": 1
  },
  {
    "HowToGet": "Shop",
    "Id": 542,
    "Season": 1
  },
  {
    "HowToGet": "Shop",
    "Id": 543,
    "Season": 1
  },
  {
    "HowToGet": "Shop",
    "Id": 546,
    "Season": 1
  },
  {
    "HowToGet": "Shop",
    "Id": 547,
    "Season": 1
  },
  {
    "HowToGet": "Shop",
    "Id": 548,
    "Season": 1
  },
  {
    "HowToGet": "Shop",
    "Id": 549,
    "Season": 1
  },
  {
    "HowToGet": "Shop",
    "Id": 541,
    "Season": 1
  },
  {
    "HowToGet": "Shop",
    "Id": 527,
    "Season": 1
  },
  {
    "HowToGet": "Shop",
    "Id": 526,
    "Season": 1
  },
  {
    "HowToGet": "Shop",
    "Id": 525,
    "Season": 1
  },
  {
    "HowToGet": "Shop",
    "Id": 501,
    "Season": 1
  },
  {
    "HowToGet": "Shop",
    "Id": 502,
    "Season": 1
  },
  {
    "HowToGet": "Shop",
    "Id": 503,
    "Season": 1
  },
  {
    "HowToGet": "Shop",
    "Id": 504,
    "Season": 1
  },
  {
    "HowToGet": "Shop",
    "Id": 505,
    "Season": 1
  },
  {
    "HowToGet": "Shop",
    "Id": 507,
    "Season": 1
  },
  {
    "HowToGet": "Shop",
    "Id": 508,
    "Season": 1
  },
  {
    "HowToGet": "Shop",
    "Id": 510,
    "Season": 1
  },
  {
    "HowToGet": "Shop",
    "Id": 513,
    "Season": 1
  },
  {
    "HowToGet": "Shop",
    "Id": 517,
    "Season": 1
  },
  {
    "HowToGet": "Shop",
    "Id": 518,
    "Season": 1
  },
  {
    "HowToGet": "Shop",
    "Id": 520,
    "Season": 1
  },
  {
    "HowToGet": "Shop",
    "Id": 521,
    "Season": 1
  },
  {
    "HowToGet": "Shop",
    "Id": 522,
    "Season": 1
  },
  {
    "HowToGet": "Shop",
    "Id": 524,
    "Season": 1
  },
  {
    "HowToGet": "Shop",
    "Id": 551,
    "Season": 1
  },
  {
    "HowToGet": "Shop",
    "Id": 499,
    "Season": 1
  },
  {
    "HowToGet": "Shop",
    "Id": 552,
    "Season": 1
  },
  {
    "HowToGet": "Shop",
    "Id": 554,
    "Season": 1
  },
  {
    "HowToGet": "Shop",
    "Id": 579,
    "Season": 1
  },
  {
    "HowToGet": "Shop",
    "Id": 580,
    "Season": 1
  },
  {
    "HowToGet": "Shop",
    "Id": 581,
    "Season": 1
  },
  {
    "HowToGet": "Shop",
    "Id": 582,
    "Season": 1
  },
  {
    "HowToGet": "Shop",
    "Id": 584,
    "Season": 1
  },
  {
    "HowToGet": "Shop",
    "Id": 586,
    "Season": 1
  },
  {
    "HowToGet": "Shop",
    "Id": 578,
    "Season": 1
  },
  {
    "HowToGet": "Shop",
    "Id": 587,
    "Season": 1
  },
  {
    "HowToGet": "Shop",
    "Id": 589,
    "Season": 1
  },
  {
    "HowToGet": "Shop",
    "Id": 591,
    "Season": 1
  },
  {
    "HowToGet": "Shop",
    "Id": 592,
    "Season": 1
  },
  {
    "HowToGet": "Shop",
    "Id": 593,
    "Season": 1
  },
  {
    "HowToGet": "Shop",
    "Id": 594,
    "Season": 1
  },
  {
    "HowToGet": "Shop",
    "Id": 595,
    "Season": 1
  },
  {
    "HowToGet": "Shop",
    "Id": 588,
    "Season": 1
  },
  {
    "HowToGet": "Shop",
    "Id": 577,
    "Season": 1
  },
  {
    "HowToGet": "Shop",
    "Id": 576,
    "Season": 1
  },
  {
    "HowToGet": "Shop",
    "Id": 574,
    "Season": 1
  },
  {
    "HowToGet": "Shop",
    "Id": 556,
    "Season": 1
  },
  {
    "HowToGet": "Shop",
    "Id": 557,
    "Season": 1
  },
  {
    "HowToGet": "Shop",
    "Id": 559,
    "Season": 1
  },
  {
    "HowToGet": "Shop",
    "Id": 560,
    "Season": 1
  },
  {
    "HowToGet": "Shop",
    "Id": 562,
    "Season": 1
  },
  {
    "HowToGet": "Shop",
    "Id": 563,
    "Season": 1
  },
  {
    "HowToGet": "Shop",
    "Id": 564,
    "Season": 1
  },
  {
    "HowToGet": "Shop",
    "Id": 565,
    "Season": 1
  },
  {
    "HowToGet": "Shop",
    "Id": 566,
    "Season": 1
  },
  {
    "HowToGet": "Shop",
    "Id": 568,
    "Season": 1
  },
  {
    "HowToGet": "Shop",
    "Id": 569,
    "Season": 1
  },
  {
    "HowToGet": "Shop",
    "Id": 570,
    "Season": 1
  },
  {
    "HowToGet": "Shop",
    "Id": 571,
    "Season": 1
  },
  {
    "HowToGet": "Shop",
    "Id": 572,
    "Season": 1
  },
  {
    "HowToGet": "Shop",
    "Id": 573,
    "Season": 1
  },
  {
    "HowToGet": "Shop",
    "Id": 553,
    "Season": 1
  },
  {
    "HowToGet": "Shop",
    "Id": 497,
    "Season": 1
  },
  {
    "HowToGet": "Shop",
    "Id": 495,
    "Season": 1
  },
  {
    "HowToGet": "Shop",
    "Id": 494,
    "Season": 1
  },
  {
    "HowToGet": "Shop",
    "Id": 423,
    "Season": 1
  },
  {
    "HowToGet": "Shop",
    "Id": 424,
    "Season": 1
  },
  {
    "HowToGet": "Shop",
    "Id": 425,
    "Season": 1
  },
  {
    "HowToGet": "Shop",
    "Id": 426,
    "Season": 1
  },
  {
    "HowToGet": "Shop",
    "Id": 428,
    "Season": 1
  },
  {
    "HowToGet": "Shop",
    "Id": 429,
    "Season": 1
  },
  {
    "HowToGet": "Shop",
    "Id": 422,
    "Season": 1
  },
  {
    "HowToGet": "Shop",
    "Id": 431,
    "Season": 1
  },
  {
    "HowToGet": "Shop",
    "Id": 433,
    "Season": 1
  },
  {
    "HowToGet": "Shop",
    "Id": 436,
    "Season": 1
  },
  {
    "HowToGet": "Shop",
    "Id": 437,
    "Season": 1
  },
  {
    "HowToGet": "Shop",
    "Id": 438,
    "Season": 1
  },
  {
    "HowToGet": "Shop",
    "Id": 439,
    "Season": 1
  },
  {
    "HowToGet": "Shop",
    "Id": 440,
    "Season": 1
  },
  {
    "HowToGet": "Shop",
    "Id": 432,
    "Season": 1
  },
  {
    "HowToGet": "Shop",
    "Id": 421,
    "Season": 1
  },
  {
    "HowToGet": "Shop",
    "Id": 420,
    "Season": 1
  },
  {
    "HowToGet": "Shop",
    "Id": 419,
    "Season": 1
  },
  {
    "HowToGet": "Shop",
    "Id": 399,
    "Season": 1
  },
  {
    "HowToGet": "Shop",
    "Id": 400,
    "Season": 1
  },
  {
    "HowToGet": "Shop",
    "Id": 402,
    "Season": 1
  },
  {
    "HowToGet": "Shop",
    "Id": 403,
    "Season": 1
  },
  {
    "HowToGet": "Shop",
    "Id": 404,
    "Season": 1
  },
  {
    "HowToGet": "Shop",
    "Id": 405,
    "Season": 1
  },
  {
    "HowToGet": "Shop",
    "Id": 406,
    "Season": 1
  },
  {
    "HowToGet": "Shop",
    "Id": 408,
    "Season": 1
  },
  {
    "HowToGet": "Shop",
    "Id": 411,
    "Season": 1
  },
  {
    "HowToGet": "Shop",
    "Id": 412,
    "Season": 1
  },
  {
    "HowToGet": "Shop",
    "Id": 414,
    "Season": 1
  },
  {
    "HowToGet": "Shop",
    "Id": 415,
    "Season": 1
  },
  {
    "HowToGet": "Shop",
    "Id": 416,
    "Season": 1
  },
  {
    "HowToGet": "Shop",
    "Id": 417,
    "Season": 1
  },
  {
    "HowToGet": "Shop",
    "Id": 418,
    "Season": 1
  },
  {
    "HowToGet": "Shop",
    "Id": 441,
    "Season": 1
  },
  {
    "HowToGet": "Shop",
    "Id": 442,
    "Season": 1
  },
  {
    "HowToGet": "Shop",
    "Id": 443,
    "Season": 1
  },
  {
    "HowToGet": "Shop",
    "Id": 444,
    "Season": 1
  },
  {
    "HowToGet": "Shop",
    "Id": 469,
    "Season": 1
  },
  {
    "HowToGet": "Shop",
    "Id": 470,
    "Season": 1
  },
  {
    "HowToGet": "Shop",
    "Id": 471,
    "Season": 1
  },
  {
    "HowToGet": "Shop",
    "Id": 473,
    "Season": 1
  },
  {
    "HowToGet": "Shop",
    "Id": 474,
    "Season": 1
  },
  {
    "HowToGet": "Shop",
    "Id": 476,
    "Season": 1
  },
  {
    "HowToGet": "Shop",
    "Id": 477,
    "Season": 1
  },
  {
    "HowToGet": "Shop",
    "Id": 480,
    "Season": 1
  },
  {
    "HowToGet": "Shop",
    "Id": 484,
    "Season": 1
  },
  {
    "HowToGet": "Shop",
    "Id": 485,
    "Season": 1
  },
  {
    "HowToGet": "Shop",
    "Id": 486,
    "Season": 1
  },
  {
    "HowToGet": "Shop",
    "Id": 488,
    "Season": 1
  },
  {
    "HowToGet": "Shop",
    "Id": 490,
    "Season": 1
  },
  {
    "HowToGet": "Shop",
    "Id": 492,
    "Season": 1
  },
  {
    "HowToGet": "Shop",
    "Id": 493,
    "Season": 1
  },
  {
    "HowToGet": "Shop",
    "Id": 468,
    "Season": 1
  },
  {
    "HowToGet": "Shop",
    "Id": 596,
    "Season": 1
  },
  {
    "HowToGet": "Shop",
    "Id": 466,
    "Season": 1
  },
  {
    "HowToGet": "Shop",
    "Id": 464,
    "Season": 1
  },
  {
    "HowToGet": "Shop",
    "Id": 445,
    "Season": 1
  },
  {
    "HowToGet": "Shop",
    "Id": 447,
    "Season": 1
  },
  {
    "HowToGet": "Shop",
    "Id": 449,
    "Season": 1
  },
  {
    "HowToGet": "Shop",
    "Id": 450,
    "Season": 1
  },
  {
    "HowToGet": "Shop",
    "Id": 451,
    "Season": 1
  },
  {
    "HowToGet": "Shop",
    "Id": 452,
    "Season": 1
  },
  {
    "HowToGet": "Shop",
    "Id": 454,
    "Season": 1
  },
  {
    "HowToGet": "Shop",
    "Id": 455,
    "Season": 1
  },
  {
    "HowToGet": "Shop",
    "Id": 457,
    "Season": 1
  },
  {
    "HowToGet": "Shop",
    "Id": 458,
    "Season": 1
  },
  {
    "HowToGet": "Shop",
    "Id": 459,
    "Season": 1
  },
  {
    "HowToGet": "Shop",
    "Id": 460,
    "Season": 1
  },
  {
    "HowToGet": "Shop",
    "Id": 461,
    "Season": 1
  },
  {
    "HowToGet": "Shop",
    "Id": 462,
    "Season": 1
  },
  {
    "HowToGet": "Shop",
    "Id": 463,
    "Season": 1
  },
  {
    "HowToGet": "Shop",
    "Id": 465,
    "Season": 1
  },
  {
    "HowToGet": "Shop",
    "Id": 598,
    "Season": 1
  },
  {
    "HowToGet": "Shop",
    "Id": 599,
    "Season": 1
  },
  {
    "HowToGet": "Shop",
    "Id": 600,
    "Season": 1
  },
  {
    "HowToGet": "Shop",
    "Id": 709,
    "Season": 1
  },
  {
    "HowToGet": "Shop",
    "Id": 710,
    "Season": 1
  },
  {
    "HowToGet": "Shop",
    "Id": 714,
    "Season": 1
  },
  {
    "HowToGet": "Shop",
    "Id": 716,
    "Season": 1
  },
  {
    "HowToGet": "Shop",
    "Id": 717,
    "Season": 1
  },
  {
    "HowToGet": "Shop",
    "Id": 718,
    "Season": 1
  },
  {
    "HowToGet": "Shop",
    "Id": 708,
    "Season": 1
  },
  {
    "HowToGet": "Shop",
    "Id": 719,
    "Season": 1
  },
  {
    "HowToGet": "Shop",
    "Id": 721,
    "Season": 1
  },
  {
    "HowToGet": "Shop",
    "Id": 722,
    "Season": 1
  },
  {
    "HowToGet": "Shop",
    "Id": 720,
    "Season": 1
  },
  {
    "HowToGet": "Shop",
    "Id": 707,
    "Season": 1
  },
  {
    "HowToGet": "Shop",
    "Id": 705,
    "Season": 1
  },
  {
    "HowToGet": "Shop",
    "Id": 704,
    "Season": 1
  },
  {
    "HowToGet": "Shop",
    "Id": 689,
    "Season": 1
  },
  {
    "HowToGet": "Shop",
    "Id": 690,
    "Season": 1
  },
  {
    "HowToGet": "Shop",
    "Id": 691,
    "Season": 1
  },
  {
    "HowToGet": "Shop",
    "Id": 692,
    "Season": 1
  },
  {
    "HowToGet": "Shop",
    "Id": 693,
    "Season": 1
  },
  {
    "HowToGet": "Shop",
    "Id": 694,
    "Season": 1
  },
  {
    "HowToGet": "Shop",
    "Id": 695,
    "Season": 1
  },
  {
    "HowToGet": "Shop",
    "Id": 696,
    "Season": 1
  },
  {
    "HowToGet": "Shop",
    "Id": 697,
    "Season": 1
  },
  {
    "HowToGet": "Shop",
    "Id": 698,
    "Season": 1
  },
  {
    "HowToGet": "Shop",
    "Id": 699,
    "Season": 1
  },
  {
    "HowToGet": "Shop",
    "Id": 700,
    "Season": 1
  },
  {
    "HowToGet": "Shop",
    "Id": 701,
    "Season": 1
  },
  {
    "HowToGet": "Shop",
    "Id": 702,
    "Season": 1
  },
  {
    "HowToGet": "Shop",
    "Id": 703,
    "Season": 1
  },
  {
    "HowToGet": "Shop",
    "Id": 3005,
    "Season": 0
  },
  {
    "HowToGet": "Shop",
    "Id": 3006,
    "Season": 0
  },
  {
    "HowToGet": "Shop",
    "Id": 3007,
    "Season": 0
  },
  {
    "HowToGet": "Shop",
    "Id": 3008,
    "Season": 0
  },
  {
    "HowToGet": "Shop",
    "Id": 3009,
    "Season": 0
  },
  {
    "HowToGet": "Shop",
    "Id": 3010,
    "Season": 0
  },
  {
    "HowToGet": "Shop",
    "Id": 3011,
    "Season": 0
  },
  {
    "HowToGet": "Shop",
    "Id": 3012,
    "Season": 0
  },
  {
    "HowToGet": "Shop",
    "Id": 3013,
    "Season": 0
  },
  {
    "HowToGet": "Shop",
    "Id": 3014,
    "Season": 0
  },
  {
    "HowToGet": "Shop",
    "Id": 3015,
    "Season": 1
  },
  {
    "HowToGet": "Other",
    "Id": 3100,
    "Season": 0
  },
  {
    "HowToGet": "Other",
    "Id": 3200,
    "Season": 0
  },
  {
    "HowToGet": "Other",
    "Id": 3201,
    "Season": 0
  },
  {
    "HowToGet": "Other",
    "Id": 3300,
    "Season": 0
  },
  {
    "HowToGet": "Shop",
    "Id": 3004,
    "Season": 0
  },
  {
    "HowToGet": "Shop",
    "Id": 688,
    "Season": 1
  },
  {
    "HowToGet": "Shop",
    "Id": 3003,
    "Season": 0
  },
  {
    "HowToGet": "Shop",
    "Id": 3001,
    "Season": 0
  },
  {
    "HowToGet": "Other",
    "Id": 2500,
    "Season": 0
  },
  {
    "HowToGet": "Shop",
    "Id": 3000,
    "Season": 0
  },
  {
    "HowToGet": "Shop",
    "Id": 3002,
    "Season": 0
  },
  {
    "HowToGet": "Shop",
    "Id": 398,
    "Season": 1
  },
  {
    "HowToGet": "Shop",
    "Id": 687,
    "Season": 1
  },
  {
    "HowToGet": "Shop",
    "Id": 684,
    "Season": 1
  },
  {
    "HowToGet": "Shop",
    "Id": 625,
    "Season": 1
  },
  {
    "HowToGet": "Shop",
    "Id": 626,
    "Season": 1
  },
  {
    "HowToGet": "Shop",
    "Id": 627,
    "Season": 1
  },
  {
    "HowToGet": "Shop",
    "Id": 629,
    "Season": 1
  },
  {
    "HowToGet": "Shop",
    "Id": 630,
    "Season": 1
  },
  {
    "HowToGet": "Shop",
    "Id": 631,
    "Season": 1
  },
  {
    "HowToGet": "Shop",
    "Id": 624,
    "Season": 1
  },
  {
    "HowToGet": "Shop",
    "Id": 632,
    "Season": 1
  },
  {
    "HowToGet": "Shop",
    "Id": 634,
    "Season": 1
  },
  {
    "HowToGet": "Shop",
    "Id": 635,
    "Season": 1
  },
  {
    "HowToGet": "Shop",
    "Id": 636,
    "Season": 1
  },
  {
    "HowToGet": "Shop",
    "Id": 638,
    "Season": 1
  },
  {
    "HowToGet": "Shop",
    "Id": 639,
    "Season": 1
  },
  {
    "HowToGet": "Shop",
    "Id": 640,
    "Season": 1
  },
  {
    "HowToGet": "Shop",
    "Id": 633,
    "Season": 1
  },
  {
    "HowToGet": "Shop",
    "Id": 623,
    "Season": 1
  },
  {
    "HowToGet": "Shop",
    "Id": 622,
    "Season": 1
  },
  {
    "HowToGet": "Shop",
    "Id": 621,
    "Season": 1
  },
  {
    "HowToGet": "Shop",
    "Id": 601,
    "Season": 1
  },
  {
    "HowToGet": "Shop",
    "Id": 602,
    "Season": 1
  },
  {
    "HowToGet": "Shop",
    "Id": 604,
    "Season": 1
  },
  {
    "HowToGet": "Shop",
    "Id": 605,
    "Season": 1
  },
  {
    "HowToGet": "Shop",
    "Id": 607,
    "Season": 1
  },
  {
    "HowToGet": "Shop",
    "Id": 608,
    "Season": 1
  },
  {
    "HowToGet": "Shop",
    "Id": 609,
    "Season": 1
  },
  {
    "HowToGet": "Shop",
    "Id": 610,
    "Season": 1
  },
  {
    "HowToGet": "Shop",
    "Id": 612,
    "Season": 1
  },
  {
    "HowToGet": "Shop",
    "Id": 613,
    "Season": 1
  },
  {
    "HowToGet": "Shop",
    "Id": 615,
    "Season": 1
  },
  {
    "HowToGet": "Shop",
    "Id": 617,
    "Season": 1
  },
  {
    "HowToGet": "Shop",
    "Id": 618,
    "Season": 1
  },
  {
    "HowToGet": "Shop",
    "Id": 620,
    "Season": 1
  },
  {
    "HowToGet": "Shop",
    "Id": 642,
    "Season": 1
  },
  {
    "HowToGet": "Shop",
    "Id": 643,
    "Season": 1
  },
  {
    "HowToGet": "Shop",
    "Id": 644,
    "Season": 1
  },
  {
    "HowToGet": "Shop",
    "Id": 645,
    "Season": 1
  },
  {
    "HowToGet": "Shop",
    "Id": 669,
    "Season": 1
  },
  {
    "HowToGet": "Shop",
    "Id": 670,
    "Season": 1
  },
  {
    "HowToGet": "Shop",
    "Id": 671,
    "Season": 1
  },
  {
    "HowToGet": "Shop",
    "Id": 672,
    "Season": 1
  },
  {
    "HowToGet": "Shop",
    "Id": 673,
    "Season": 1
  },
  {
    "HowToGet": "Shop",
    "Id": 674,
    "Season": 1
  },
  {
    "HowToGet": "Shop",
    "Id": 675,
    "Season": 1
  },
  {
    "HowToGet": "Shop",
    "Id": 676,
    "Season": 1
  },
  {
    "HowToGet": "Shop",
    "Id": 677,
    "Season": 1
  },
  {
    "HowToGet": "Shop",
    "Id": 678,
    "Season": 1
  },
  {
    "HowToGet": "Shop",
    "Id": 679,
    "Season": 1
  },
  {
    "HowToGet": "Shop",
    "Id": 680,
    "Season": 1
  },
  {
    "HowToGet": "Shop",
    "Id": 681,
    "Season": 1
  },
  {
    "HowToGet": "Shop",
    "Id": 682,
    "Season": 1
  },
  {
    "HowToGet": "Shop",
    "Id": 683,
    "Season": 1
  },
  {
    "HowToGet": "Shop",
    "Id": 667,
    "Season": 1
  },
  {
    "HowToGet": "Shop",
    "Id": 686,
    "Season": 1
  },
  {
    "HowToGet": "Shop",
    "Id": 666,
    "Season": 1
  },
  {
    "HowToGet": "Shop",
    "Id": 664,
    "Season": 1
  },
  {
    "HowToGet": "Shop",
    "Id": 646,
    "Season": 1
  },
  {
    "HowToGet": "Shop",
    "Id": 647,
    "Season": 1
  },
  {
    "HowToGet": "Shop",
    "Id": 648,
    "Season": 1
  },
  {
    "HowToGet": "Shop",
    "Id": 650,
    "Season": 1
  },
  {
    "HowToGet": "Shop",
    "Id": 651,
    "Season": 1
  },
  {
    "HowToGet": "Shop",
    "Id": 652,
    "Season": 1
  },
  {
    "HowToGet": "Shop",
    "Id": 653,
    "Season": 1
  },
  {
    "HowToGet": "Shop",
    "Id": 654,
    "Season": 1
  },
  {
    "HowToGet": "Shop",
    "Id": 655,
    "Season": 1
  },
  {
    "HowToGet": "Shop",
    "Id": 656,
    "Season": 1
  },
  {
    "HowToGet": "Shop",
    "Id": 657,
    "Season": 1
  },
  {
    "HowToGet": "Shop",
    "Id": 660,
    "Season": 1
  },
  {
    "HowToGet": "Shop",
    "Id": 661,
    "Season": 1
  },
  {
    "HowToGet": "Shop",
    "Id": 662,
    "Season": 1
  },
  {
    "HowToGet": "Shop",
    "Id": 663,
    "Season": 1
  },
  {
    "HowToGet": "Shop",
    "Id": 665,
    "Season": 1
  },
  {
    "HowToGet": "Shop",
    "Id": 397,
    "Season": 1
  },
  {
    "HowToGet": "Shop",
    "Id": 394,
    "Season": 1
  },
  {
    "HowToGet": "Shop",
    "Id": 164,
    "Season": 0
  },
  {
    "HowToGet": "Shop",
    "Id": 165,
    "Season": 0
  },
  {
    "HowToGet": "Shop",
    "Id": 166,
    "Season": 0
  },
  {
    "HowToGet": "Shop",
    "Id": 167,
    "Season": 0
  },
  {
    "HowToGet": "Shop",
    "Id": 168,
    "Season": 0
  },
  {
    "HowToGet": "Shop",
    "Id": 169,
    "Season": 0
  },
  {
    "HowToGet": "Shop",
    "Id": 163,
    "Season": 0
  },
  {
    "HowToGet": "Shop",
    "Id": 170,
    "Season": 0
  },
  {
    "HowToGet": "Shop",
    "Id": 172,
    "Season": 0
  },
  {
    "HowToGet": "Shop",
    "Id": 173,
    "Season": 0
  },
  {
    "HowToGet": "Shop",
    "Id": 174,
    "Season": 0
  },
  {
    "HowToGet": "Shop",
    "Id": 175,
    "Season": 0
  },
  {
    "HowToGet": "Shop",
    "Id": 177,
    "Season": 0
  },
  {
    "HowToGet": "Shop",
    "Id": 178,
    "Season": 0
  },
  {
    "HowToGet": "Shop",
    "Id": 171,
    "Season": 0
  },
  {
    "HowToGet": "Shop",
    "Id": 162,
    "Season": 0
  },
  {
    "HowToGet": "Shop",
    "Id": 161,
    "Season": 0
  },
  {
    "HowToGet": "Shop",
    "Id": 160,
    "Season": 0
  },
  {
    "HowToGet": "Shop",
    "Id": 144,
    "Season": 0
  },
  {
    "HowToGet": "Shop",
    "Id": 145,
    "Season": 0
  },
  {
    "HowToGet": "Shop",
    "Id": 146,
    "Season": 0
  },
  {
    "HowToGet": "Shop",
    "Id": 147,
    "Season": 0
  },
  {
    "HowToGet": "Shop",
    "Id": 148,
    "Season": 0
  },
  {
    "HowToGet": "Shop",
    "Id": 149,
    "Season": 0
  },
  {
    "HowToGet": "Shop",
    "Id": 150,
    "Season": 0
  },
  {
    "HowToGet": "Shop",
    "Id": 151,
    "Season": 0
  },
  {
    "HowToGet": "Shop",
    "Id": 152,
    "Season": 0
  },
  {
    "HowToGet": "Shop",
    "Id": 154,
    "Season": 0
  },
  {
    "HowToGet": "Shop",
    "Id": 155,
    "Season": 0
  },
  {
    "HowToGet": "Shop",
    "Id": 156,
    "Season": 0
  },
  {
    "HowToGet": "Shop",
    "Id": 157,
    "Season": 0
  },
  {
    "HowToGet": "Shop",
    "Id": 158,
    "Season": 0
  },
  {
    "HowToGet": "Shop",
    "Id": 159,
    "Season": 0
  },
  {
    "HowToGet": "Shop",
    "Id": 179,
    "Season": 0
  },
  {
    "HowToGet": "Shop",
    "Id": 143,
    "Season": 0
  },
  {
    "HowToGet": "Shop",
    "Id": 180,
    "Season": 0
  },
  {
    "HowToGet": "Shop",
    "Id": 182,
    "Season": 0
  },
  {
    "HowToGet": "Shop",
    "Id": 206,
    "Season": 0
  },
  {
    "HowToGet": "Shop",
    "Id": 207,
    "Season": 0
  },
  {
    "HowToGet": "Shop",
    "Id": 208,
    "Season": 0
  },
  {
    "HowToGet": "Shop",
    "Id": 209,
    "Season": 0
  },
  {
    "HowToGet": "Shop",
    "Id": 210,
    "Season": 0
  },
  {
    "HowToGet": "Shop",
    "Id": 211,
    "Season": 0
  },
  {
    "HowToGet": "Shop",
    "Id": 205,
    "Season": 0
  },
  {
    "HowToGet": "Shop",
    "Id": 212,
    "Season": 0
  },
  {
    "HowToGet": "Shop",
    "Id": 214,
    "Season": 0
  },
  {
    "HowToGet": "Shop",
    "Id": 215,
    "Season": 0
  },
  {
    "HowToGet": "Shop",
    "Id": 216,
    "Season": 0
  },
  {
    "HowToGet": "Shop",
    "Id": 217,
    "Season": 0
  },
  {
    "HowToGet": "Shop",
    "Id": 219,
    "Season": 0
  },
  {
    "HowToGet": "Shop",
    "Id": 220,
    "Season": 0
  },
  {
    "HowToGet": "Shop",
    "Id": 213,
    "Season": 0
  },
  {
    "HowToGet": "Shop",
    "Id": 204,
    "Season": 0
  },
  {
    "HowToGet": "Shop",
    "Id": 203,
    "Season": 0
  },
  {
    "HowToGet": "Shop",
    "Id": 202,
    "Season": 0
  },
  {
    "HowToGet": "Shop",
    "Id": 183,
    "Season": 0
  },
  {
    "HowToGet": "Shop",
    "Id": 184,
    "Season": 0
  },
  {
    "HowToGet": "Shop",
    "Id": 185,
    "Season": 0
  },
  {
    "HowToGet": "Shop",
    "Id": 186,
    "Season": 0
  },
  {
    "HowToGet": "Shop",
    "Id": 187,
    "Season": 0
  },
  {
    "HowToGet": "Shop",
    "Id": 188,
    "Season": 0
  },
  {
    "HowToGet": "Shop",
    "Id": 189,
    "Season": 0
  },
  {
    "HowToGet": "Shop",
    "Id": 191,
    "Season": 0
  },
  {
    "HowToGet": "Shop",
    "Id": 193,
    "Season": 0
  },
  {
    "HowToGet": "Shop",
    "Id": 194,
    "Season": 0
  },
  {
    "HowToGet": "Shop",
    "Id": 195,
    "Season": 0
  },
  {
    "HowToGet": "Shop",
    "Id": 196,
    "Season": 0
  },
  {
    "HowToGet": "Shop",
    "Id": 197,
    "Season": 0
  },
  {
    "HowToGet": "Shop",
    "Id": 200,
    "Season": 0
  },
  {
    "HowToGet": "Shop",
    "Id": 201,
    "Season": 0
  },
  {
    "HowToGet": "Shop",
    "Id": 181,
    "Season": 0
  },
  {
    "HowToGet": "Catalog",
    "Id": 142,
    "Season": 0
  },
  {
    "HowToGet": "Shop",
    "Id": 141,
    "Season": 0
  },
  {
    "HowToGet": "Shop",
    "Id": 140,
    "Season": 0
  },
  {
    "HowToGet": "Shop",
    "Id": 45,
    "Season": 0
  },
  {
    "HowToGet": "Shop",
    "Id": 46,
    "Season": 1
  },
  {
    "HowToGet": "Shop",
    "Id": 60,
    "Season": 0
  },
  {
    "HowToGet": "Shop",
    "Id": 61,
    "Season": 0
  },
  {
    "HowToGet": "Shop",
    "Id": 63,
    "Season": 0
  },
  {
    "HowToGet": "Shop",
    "Id": 64,
    "Season": 0
  },
  {
    "HowToGet": "Shop",
    "Id": 100,
    "Season": 0
  },
  {
    "HowToGet": "Shop",
    "Id": 101,
    "Season": 0
  },
  {
    "HowToGet": "Shop",
    "Id": 62,
    "Season": 0
  },
  {
    "HowToGet": "Shop",
    "Id": 40,
    "Season": 1
  },
  {
    "HowToGet": "Shop",
    "Id": 1,
    "Season": 0
  },
  {
    "HowToGet": "Shop",
    "Id": 2,
    "Season": 0
  },
  {
    "HowToGet": "Shop",
    "Id": 3,
    "Season": 0
  },
  {
    "HowToGet": "Shop",
    "Id": 5,
    "Season": 0
  },
  {
    "HowToGet": "Shop",
    "Id": 8,
    "Season": 0
  },
  {
    "HowToGet": "Shop",
    "Id": 9,
    "Season": 1
  },
  {
    "HowToGet": "Shop",
    "Id": 10,
    "Season": 1
  },
  {
    "HowToGet": "Shop",
    "Id": 11,
    "Season": 0
  },
  {
    "HowToGet": "Shop",
    "Id": 12,
    "Season": 1
  },
  {
    "HowToGet": "Shop",
    "Id": 13,
    "Season": 1
  },
  {
    "HowToGet": "Shop",
    "Id": 14,
    "Season": 0
  },
  {
    "HowToGet": "Shop",
    "Id": 102,
    "Season": 0
  },
  {
    "HowToGet": "Shop",
    "Id": 103,
    "Season": 0
  },
  {
    "HowToGet": "Shop",
    "Id": 104,
    "Season": 0
  },
  {
    "HowToGet": "Shop",
    "Id": 105,
    "Season": 0
  },
  {
    "HowToGet": "Shop",
    "Id": 125,
    "Season": 0
  },
  {
    "HowToGet": "Shop",
    "Id": 126,
    "Season": 0
  },
  {
    "HowToGet": "Shop",
    "Id": 127,
    "Season": 0
  },
  {
    "HowToGet": "Shop",
    "Id": 128,
    "Season": 0
  },
  {
    "HowToGet": "Shop",
    "Id": 129,
    "Season": 0
  },
  {
    "HowToGet": "Shop",
    "Id": 130,
    "Season": 0
  },
  {
    "HowToGet": "Shop",
    "Id": 131,
    "Season": 0
  },
  {
    "HowToGet": "Shop",
    "Id": 132,
    "Season": 0
  },
  {
    "HowToGet": "Shop",
    "Id": 133,
    "Season": 0
  },
  {
    "HowToGet": "Shop",
    "Id": 134,
    "Season": 0
  },
  {
    "HowToGet": "Shop",
    "Id": 135,
    "Season": 0
  },
  {
    "HowToGet": "Shop",
    "Id": 136,
    "Season": 0
  },
  {
    "HowToGet": "Shop",
    "Id": 137,
    "Season": 0
  },
  {
    "HowToGet": "Shop",
    "Id": 138,
    "Season": 0
  },
  {
    "HowToGet": "Shop",
    "Id": 139,
    "Season": 0
  },
  {
    "HowToGet": "Shop",
    "Id": 124,
    "Season": 0
  },
  {
    "HowToGet": "Shop",
    "Id": 221,
    "Season": 0
  },
  {
    "HowToGet": "Shop",
    "Id": 123,
    "Season": 0
  },
  {
    "HowToGet": "Shop",
    "Id": 121,
    "Season": 0
  },
  {
    "HowToGet": "Shop",
    "Id": 106,
    "Season": 0
  },
  {
    "HowToGet": "Shop",
    "Id": 107,
    "Season": 0
  },
  {
    "HowToGet": "Shop",
    "Id": 108,
    "Season": 0
  },
  {
    "HowToGet": "Shop",
    "Id": 109,
    "Season": 0
  },
  {
    "HowToGet": "Shop",
    "Id": 110,
    "Season": 0
  },
  {
    "HowToGet": "Shop",
    "Id": 111,
    "Season": 0
  },
  {
    "HowToGet": "Shop",
    "Id": 112,
    "Season": 0
  },
  {
    "HowToGet": "Shop",
    "Id": 113,
    "Season": 0
  },
  {
    "HowToGet": "Shop",
    "Id": 114,
    "Season": 0
  },
  {
    "HowToGet": "Shop",
    "Id": 115,
    "Season": 0
  },
  {
    "HowToGet": "Shop",
    "Id": 116,
    "Season": 1
  },
  {
    "HowToGet": "Shop",
    "Id": 117,
    "Season": 0
  },
  {
    "HowToGet": "Shop",
    "Id": 118,
    "Season": 0
  },
  {
    "HowToGet": "Shop",
    "Id": 119,
    "Season": 0
  },
  {
    "HowToGet": "Shop",
    "Id": 120,
    "Season": 0
  },
  {
    "HowToGet": "Shop",
    "Id": 122,
    "Season": 0
  },
  {
    "HowToGet": "Shop",
    "Id": 222,
    "Season": 0
  },
  {
    "HowToGet": "Shop",
    "Id": 224,
    "Season": 0
  },
  {
    "HowToGet": "Shop",
    "Id": 225,
    "Season": 0
  },
  {
    "HowToGet": "Shop",
    "Id": 326,
    "Season": 1
  },
  {
    "HowToGet": "Shop",
    "Id": 329,
    "Season": 1
  },
  {
    "HowToGet": "Shop",
    "Id": 330,
    "Season": 1
  },
  {
    "HowToGet": "Shop",
    "Id": 332,
    "Season": 1
  },
  {
    "HowToGet": "Shop",
    "Id": 334,
    "Season": 1
  },
  {
    "HowToGet": "Shop",
    "Id": 335,
    "Season": 1
  },
  {
    "HowToGet": "Shop",
    "Id": 325,
    "Season": 1
  },
  {
    "HowToGet": "Shop",
    "Id": 336,
    "Season": 1
  },
  {
    "HowToGet": "Shop",
    "Id": 338,
    "Season": 1
  },
  {
    "HowToGet": "Shop",
    "Id": 339,
    "Season": 1
  },
  {
    "HowToGet": "Shop",
    "Id": 340,
    "Season": 1
  },
  {
    "HowToGet": "Shop",
    "Id": 341,
    "Season": 1
  },
  {
    "HowToGet": "Shop",
    "Id": 343,
    "Season": 1
  },
  {
    "HowToGet": "Shop",
    "Id": 344,
    "Season": 1
  },
  {
    "HowToGet": "Shop",
    "Id": 337,
    "Season": 1
  },
  {
    "HowToGet": "Shop",
    "Id": 324,
    "Season": 1
  },
  {
    "HowToGet": "Shop",
    "Id": 323,
    "Season": 1
  },
  {
    "HowToGet": "Shop",
    "Id": 322,
    "Season": 1
  },
  {
    "HowToGet": "Shop",
    "Id": 307,
    "Season": 1
  },
  {
    "HowToGet": "Shop",
    "Id": 308,
    "Season": 1
  },
  {
    "HowToGet": "Shop",
    "Id": 309,
    "Season": 1
  },
  {
    "HowToGet": "Shop",
    "Id": 310,
    "Season": 1
  },
  {
    "HowToGet": "Shop",
    "Id": 311,
    "Season": 1
  },
  {
    "HowToGet": "Shop",
    "Id": 312,
    "Season": 1
  },
  {
    "HowToGet": "Shop",
    "Id": 313,
    "Season": 1
  },
  {
    "HowToGet": "Shop",
    "Id": 314,
    "Season": 1
  },
  {
    "HowToGet": "Shop",
    "Id": 315,
    "Season": 1
  },
  {
    "HowToGet": "Shop",
    "Id": 316,
    "Season": 1
  },
  {
    "HowToGet": "Shop",
    "Id": 317,
    "Season": 1
  },
  {
    "HowToGet": "Shop",
    "Id": 318,
    "Season": 1
  },
  {
    "HowToGet": "Shop",
    "Id": 319,
    "Season": 1
  },
  {
    "HowToGet": "Shop",
    "Id": 320,
    "Season": 1
  },
  {
    "HowToGet": "Shop",
    "Id": 321,
    "Season": 1
  },
  {
    "HowToGet": "Shop",
    "Id": 345,
    "Season": 1
  },
  {
    "HowToGet": "Shop",
    "Id": 347,
    "Season": 1
  },
  {
    "HowToGet": "Shop",
    "Id": 348,
    "Season": 1
  },
  {
    "HowToGet": "Shop",
    "Id": 350,
    "Season": 1
  },
  {
    "HowToGet": "Shop",
    "Id": 375,
    "Season": 1
  },
  {
    "HowToGet": "Shop",
    "Id": 376,
    "Season": 1
  },
  {
    "HowToGet": "Shop",
    "Id": 377,
    "Season": 1
  },
  {
    "HowToGet": "Shop",
    "Id": 378,
    "Season": 1
  },
  {
    "HowToGet": "Shop",
    "Id": 379,
    "Season": 1
  },
  {
    "HowToGet": "Shop",
    "Id": 381,
    "Season": 1
  },
  {
    "HowToGet": "Shop",
    "Id": 382,
    "Season": 1
  },
  {
    "HowToGet": "Shop",
    "Id": 385,
    "Season": 1
  },
  {
    "HowToGet": "Shop",
    "Id": 386,
    "Season": 1
  },
  {
    "HowToGet": "Shop",
    "Id": 387,
    "Season": 1
  },
  {
    "HowToGet": "Shop",
    "Id": 388,
    "Season": 1
  },
  {
    "HowToGet": "Shop",
    "Id": 389,
    "Season": 1
  },
  {
    "HowToGet": "Shop",
    "Id": 390,
    "Season": 1
  },
  {
    "HowToGet": "Shop",
    "Id": 391,
    "Season": 1
  },
  {
    "HowToGet": "Shop",
    "Id": 393,
    "Season": 1
  },
  {
    "HowToGet": "Shop",
    "Id": 374,
    "Season": 1
  },
  {
    "HowToGet": "Shop",
    "Id": 306,
    "Season": 1
  },
  {
    "HowToGet": "Shop",
    "Id": 372,
    "Season": 1
  },
  {
    "HowToGet": "Shop",
    "Id": 370,
    "Season": 1
  },
  {
    "HowToGet": "Shop",
    "Id": 352,
    "Season": 1
  },
  {
    "HowToGet": "Shop",
    "Id": 353,
    "Season": 1
  },
  {
    "HowToGet": "Shop",
    "Id": 354,
    "Season": 1
  },
  {
    "HowToGet": "Shop",
    "Id": 357,
    "Season": 1
  },
  {
    "HowToGet": "Shop",
    "Id": 358,
    "Season": 1
  },
  {
    "HowToGet": "Shop",
    "Id": 359,
    "Season": 1
  },
  {
    "HowToGet": "Shop",
    "Id": 360,
    "Season": 1
  },
  {
    "HowToGet": "Shop",
    "Id": 361,
    "Season": 1
  },
  {
    "HowToGet": "Shop",
    "Id": 362,
    "Season": 1
  },
  {
    "HowToGet": "Shop",
    "Id": 363,
    "Season": 1
  },
  {
    "HowToGet": "Shop",
    "Id": 364,
    "Season": 1
  },
  {
    "HowToGet": "Shop",
    "Id": 366,
    "Season": 1
  },
  {
    "HowToGet": "Shop",
    "Id": 367,
    "Season": 1
  },
  {
    "HowToGet": "Shop",
    "Id": 368,
    "Season": 1
  },
  {
    "HowToGet": "Shop",
    "Id": 369,
    "Season": 1
  },
  {
    "HowToGet": "Shop",
    "Id": 371,
    "Season": 1
  },
  {
    "HowToGet": "Shop",
    "Id": 395,
    "Season": 1
  },
  {
    "HowToGet": "Shop",
    "Id": 305,
    "Season": 1
  },
  {
    "HowToGet": "Shop",
    "Id": 303,
    "Season": 1
  },
  {
    "HowToGet": "Shop",
    "Id": 245,
    "Season": 0
  },
  {
    "HowToGet": "Shop",
    "Id": 246,
    "Season": 0
  },
  {
    "HowToGet": "Shop",
    "Id": 247,
    "Season": 0
  },
  {
    "HowToGet": "Shop",
    "Id": 248,
    "Season": 0
  },
  {
    "HowToGet": "Shop",
    "Id": 249,
    "Season": 0
  },
  {
    "HowToGet": "Shop",
    "Id": 250,
    "Season": 0
  },
  {
    "HowToGet": "Shop",
    "Id": 244,
    "Season": 0
  },
  {
    "HowToGet": "Shop",
    "Id": 251,
    "Season": 0
  },
  {
    "HowToGet": "Shop",
    "Id": 254,
    "Season": 0
  },
  {
    "HowToGet": "Shop",
    "Id": 255,
    "Season": 0
  },
  {
    "HowToGet": "Shop",
    "Id": 256,
    "Season": 0
  },
  {
    "HowToGet": "Shop",
    "Id": 257,
    "Season": 0
  },
  {
    "HowToGet": "Shop",
    "Id": 258,
    "Season": 0
  },
  {
    "HowToGet": "Shop",
    "Id": 259,
    "Season": 0
  },
  {
    "HowToGet": "Shop",
    "Id": 253,
    "Season": 0
  },
  {
    "HowToGet": "Shop",
    "Id": 243,
    "Season": 0
  },
  {
    "HowToGet": "Shop",
    "Id": 242,
    "Season": 0
  },
  {
    "HowToGet": "Shop",
    "Id": 241,
    "Season": 0
  },
  {
    "HowToGet": "Shop",
    "Id": 226,
    "Season": 0
  },
  {
    "HowToGet": "Shop",
    "Id": 227,
    "Season": 0
  },
  {
    "HowToGet": "Shop",
    "Id": 228,
    "Season": 0
  },
  {
    "HowToGet": "Shop",
    "Id": 229,
    "Season": 0
  },
  {
    "HowToGet": "Shop",
    "Id": 230,
    "Season": 0
  },
  {
    "HowToGet": "Shop",
    "Id": 231,
    "Season": 0
  },
  {
    "HowToGet": "Shop",
    "Id": 232,
    "Season": 0
  },
  {
    "HowToGet": "Shop",
    "Id": 233,
    "Season": 0
  },
  {
    "HowToGet": "Shop",
    "Id": 234,
    "Season": 0
  },
  {
    "HowToGet": "Shop",
    "Id": 235,
    "Season": 0
  },
  {
    "HowToGet": "Shop",
    "Id": 236,
    "Season": 0
  },
  {
    "HowToGet": "Shop",
    "Id": 237,
    "Season": 0
  },
  {
    "HowToGet": "Shop",
    "Id": 238,
    "Season": 0
  },
  {
    "HowToGet": "Shop",
    "Id": 239,
    "Season": 0
  },
  {
    "HowToGet": "Shop",
    "Id": 240,
    "Season": 0
  },
  {
    "HowToGet": "Shop",
    "Id": 260,
    "Season": 0
  },
  {
    "HowToGet": "Shop",
    "Id": 261,
    "Season": 0
  },
  {
    "HowToGet": "Shop",
    "Id": 262,
    "Season": 0
  },
  {
    "HowToGet": "Shop",
    "Id": 263,
    "Season": 0
  },
  {
    "HowToGet": "Shop",
    "Id": 284,
    "Season": 1
  },
  {
    "HowToGet": "Shop",
    "Id": 288,
    "Season": 1
  },
  {
    "HowToGet": "Shop",
    "Id": 289,
    "Season": 1
  },
  {
    "HowToGet": "Shop",
    "Id": 290,
    "Season": 1
  },
  {
    "HowToGet": "Shop",
    "Id": 291,
    "Season": 1
  },
  {
    "HowToGet": "Shop",
    "Id": 292,
    "Season": 1
  },
  {
    "HowToGet": "Shop",
    "Id": 293,
    "Season": 1
  },
  {
    "HowToGet": "Shop",
    "Id": 294,
    "Season": 1
  },
  {
    "HowToGet": "Shop",
    "Id": 295,
    "Season": 1
  },
  {
    "HowToGet": "Shop",
    "Id": 296,
    "Season": 1
  },
  {
    "HowToGet": "Shop",
    "Id": 297,
    "Season": 1
  },
  {
    "HowToGet": "Shop",
    "Id": 301,
    "Season": 1
  },
  {
    "HowToGet": "Shop",
    "Id": 283,
    "Season": 1
  },
  {
    "HowToGet": "Shop",
    "Id": 304,
    "Season": 1
  },
  {
    "HowToGet": "Shop",
    "Id": 282,
    "Season": 1
  },
  {
    "HowToGet": "Shop",
    "Id": 279,
    "Season": 1
  },
  {
    "HowToGet": "Shop",
    "Id": 264,
    "Season": 0
  },
  {
    "HowToGet": "Shop",
    "Id": 265,
    "Season": 0
  },
  {
    "HowToGet": "Shop",
    "Id": 266,
    "Season": 0
  },
  {
    "HowToGet": "Shop",
    "Id": 267,
    "Season": 0
  },
  {
    "HowToGet": "Shop",
    "Id": 268,
    "Season": 0
  },
  {
    "HowToGet": "Shop",
    "Id": 269,
    "Season": 0
  },
  {
    "HowToGet": "Shop",
    "Id": 270,
    "Season": 0
  },
  {
    "HowToGet": "Shop",
    "Id": 271,
    "Season": 0
  },
  {
    "HowToGet": "Shop",
    "Id": 272,
    "Season": 1
  },
  {
    "HowToGet": "Shop",
    "Id": 273,
    "Season": 1
  },
  {
    "HowToGet": "Shop",
    "Id": 274,
    "Season": 1
  },
  {
    "HowToGet": "Shop",
    "Id": 275,
    "Season": 1
  },
  {
    "HowToGet": "Shop",
    "Id": 276,
    "Season": 1
  },
  {
    "HowToGet": "Catalog",
    "Id": 277,
    "Season": 1
  },
  {
    "HowToGet": "Shop",
    "Id": 278,
    "Season": 1
  },
  {
    "HowToGet": "Shop",
    "Id": 281,
    "Season": 1
  }
]